intellipy/__init__.py
intellipy/__main__.py
IntelliPy-0.10.6.dist-info/METADATA
IntelliPy-0.10.6.dist-info/WHEEL
IntelliPy-0.10.6.dist-info/top_level.txt
IntelliPy-0.10.6.dist-info/RECORD
