Metadata-Version: 2.1
Name: IntelliPy
Version: 0.10.6
Summary: Automatic IntelliCage data analysis using Python
Home-page: https://github.com/NiRuff/IntelliPy
Author: Nicolas Ruffini
Author-email: n.ruffini@gmx.de
Classifier: Programming Language :: Python :: 3
Classifier: License :: OSI Approved :: MIT License
Classifier: Operating System :: OS Independent
Requires-Python: >=3.9
Requires-Dist: numpy >=2.0.0
Requires-Dist: pandas >=2.2.2
Requires-Dist: xlsxwriter >=3.2.0
Requires-Dist: matplotlib >=3.9.1
Requires-Dist: seaborn >=0.13.2
